fundrives/__init__.py
fundrives/quark/__init__.py
fundrives/quark/manage.py
fundrive_quark-1.0.2.dist-info/METADATA
fundrive_quark-1.0.2.dist-info/WHEEL
fundrive_quark-1.0.2.dist-info/top_level.txt
fundrive_quark-1.0.2.dist-info/RECORD
