Metadata-Version: 2.1
Name: fundrive-quark
Version: 1.0.2
Summary: fundrive-quark
Author-email: niuliangtao <farfarfun@qq.com>
Requires-Python: >=3.8
Requires-Dist: funutil>=1.0.46
